{
  "project_info": {
    "project_number": "1086990051888",
    "firebase_url": "https://freshly-booked.firebaseio.com",
    "project_id": "freshly-booked",
    "storage_bucket": "freshly-booked.appspot.com"
  },
  "client": [
    {
      "client_info": {
        "mobilesdk_app_id": "1:1086990051888:android:15e65accab911b16",
        "android_client_info": {
          "package_name": "com.theateam.freshlybooked"
        }
      },
      "oauth_client": [
        {
          "client_id": "1086990051888-0pvrp1c5ehv5cer2k5o166bpj6vknqdj.apps.googleusercontent.com",
          "client_type": 3
        }
      ],
      "api_key": [
        {
          "current_key": "AIzaSyC-wm-U0ZRSI0eyOvNiqJQi6QKibD1ZQEc"
        }
      ],
      "services": {
        "analytics_service": {
          "status": 1
        },
        "appinvite_service": {
          "status": 1,
          "other_platform_oauth_client": []
        },
        "ads_service": {
          "status": 2
        }
      }
    }
  ],
  "configuration_version": "1"
}